README.md
setup.py
superflore/CacheManager.py
superflore/PackageMetadata.py
superflore/TempfileManager.py
superflore/__init__.py
superflore/docker.py
superflore/exceptions.py
superflore/generate_installers.py
superflore/parser.py
superflore/repo_instance.py
superflore/rosdep_support.py
superflore/utils.py
superflore.egg-info/PKG-INFO
superflore.egg-info/SOURCES.txt
superflore.egg-info/dependency_links.txt
superflore.egg-info/entry_points.txt
superflore.egg-info/requires.txt
superflore.egg-info/top_level.txt
superflore/generators/__init__.py
superflore/generators/bitbake/__init__.py
superflore/generators/bitbake/gen_packages.py
superflore/generators/bitbake/oe_query.py
superflore/generators/bitbake/ros_meta.py
superflore/generators/bitbake/run.py
superflore/generators/bitbake/yocto_recipe.py
superflore/generators/ebuild/__init__.py
superflore/generators/ebuild/ebuild.py
superflore/generators/ebuild/gen_packages.py
superflore/generators/ebuild/metadata_xml.py
superflore/generators/ebuild/overlay_instance.py
superflore/generators/ebuild/run.py
superflore/test_integration/__init__.py
superflore/test_integration/gentoo/__init__.py
superflore/test_integration/gentoo/build_base.py
superflore/test_integration/gentoo/main.py