Metadata-Version: 1.2
Name: superflore
Version: 0.3.0
Summary: Super Bloom
Home-page: https://github.com/ros-infrastructure/superflore
Author: Hunter L. Allen
Author-email: hunterlallen@protonmail.com
License: Apache 2.0
Keywords: ROS
Platform: UNKNOWN
Classifier: Programming Language :: Python
Classifier: License :: OSI Approved :: Apache Software License
Classifier: License :: OSI Approved :: MIT License
Requires-Python: >=3
